praxis_timeseries_client/__init__.py
praxis_timeseries_client/darts/__init__.py
praxis_timeseries_client/darts/darts_backtest.py
praxis_timeseries_client/darts/darts_forecast.py
praxis_timeseries_client/darts/darts_interface.py
praxis_timeseries_client/darts/utils.py
praxis_timeseries_client/data/__init__.py
praxis_timeseries_client-0.0.4.dist-info/LICENSE
praxis_timeseries_client-0.0.4.dist-info/METADATA
praxis_timeseries_client-0.0.4.dist-info/WHEEL
praxis_timeseries_client-0.0.4.dist-info/top_level.txt
praxis_timeseries_client-0.0.4.dist-info/RECORD
