Metadata-Version: 2.1
Name: praxis-timeseries-client
Version: 0.0.4
Summary: A Darts Time Series client for facilitating model development and data exploration.
Home-page: https://github.com/praxis-pioneering/praxis-timeseries-client.git
Author: evan kirkiles
Author-email: evan@praxispioneering.com
Classifier: Programming Language :: Python :: 3
Classifier: Operating System :: OS Independent
Requires-Python: >=3.7
License-File: LICENSE
